easy_os/__init__.py
easy_os/easy_os_helpers.py
easy_panda/__init__.py
easy_panda/easy_panda.py
easy_panda/easy_panda_helpers.py
easy_panda/easy_panda_type.py
easy_request/__init__.py
easy_request/easy_get_request.py
easy_request/easy_method_type.py
easy_spark/__init__.py
easy_spark/easy_con_opetator.py
easy_spark/easy_con_value.py
easy_spark/easy_format_type.py
easy_spark/easy_merge_option_type.py
easy_spark/easy_merge_type.py
easy_spark/easy_save_mode_type.py
easy_spark/easy_save_type.py
easy_spark/easy_spark_conf.py
easy_spark/easy_spark_delta_helpers.py
easy_spark/easy_spark_delta_table.py
easy_spark/easy_spark_df.py
easy_spark/easy_spark_df_optimize.py
easy_spark/easy_spark_instance.py
easy_spark/easy_spark_mssparkutils_helpers.py
easy_spark/easy_sql_builder.py
easy_spark_fs/__init__.py
easy_spark_fs/easy_file_detail.py
easy_spark_fs/easy_spark_catalog.py
easy_spark_fs/easy_spark_fs_file.py
easy_spark_fs/easy_spark_fs_path.py
easy_spark_fs/easy_spark_hoop.py
easy_spark_path/__init__.py
easy_spark_path/easy_file_type.py
easy_spark_path/easy_path.py
easy_spark_path/easy_spark_directory_path.py
easy_spark_path/easy_spark_file_path.py
easy_spark_path/easy_spark_lh_path.py
easy_spark_path/easy_spark_simple_table_path.py
easy_spark_path/easy_spark_table_path.py
easy_spark_path/easy_spark_wh_path.py
easy_spark_path/easy_warehouse_type.py
easy_sql_data_access/__init__.py
easy_sql_data_access/easy_open_data_connection.py
easy_sql_data_access/easy_sql_connection_factory.py
easy_sql_data_access/easy_sql_data_access.py
easy_sql_data_access/easy_sql_data_access_factory.py
easy_sql_data_access/easy_sql_data_connection_builder.py
easy_sql_data_access/easy_sql_data_entity_dict.py
easy_sql_data_access/easy_sql_data_entity_type.py
easy_sql_data_access/easy_sql_manage_data_access.py
easy_utils/__init__.py
easy_utils/easy_data_utils.py
easy_utils/easy_singleton.py
easy_utils/easy_utils.py
e_o_easy_stuff-5.0.1.dist-info/METADATA
e_o_easy_stuff-5.0.1.dist-info/WHEEL
e_o_easy_stuff-5.0.1.dist-info/top_level.txt
e_o_easy_stuff-5.0.1.dist-info/RECORD
