Metadata-Version: 2.1
Name: e-o-easy_stuff
Version: 5.0.1
Summary: Easy tools
Author: Gideon
Keywords: pyspark
Classifier: Development Status :: 1 - Planning
Classifier: Intended Audience :: Developers
Classifier: Programming Language :: Python :: 3
Classifier: Operating System :: Unix
Classifier: Operating System :: MacOS :: MacOS X
Classifier: Operating System :: Microsoft :: Windows
Requires-Dist: pyspark
